tiny_json_log/__init__.py
tiny_json_log-0.1.0.dist-info/LICENSE
tiny_json_log-0.1.0.dist-info/METADATA
tiny_json_log-0.1.0.dist-info/WHEEL
tiny_json_log-0.1.0.dist-info/RECORD
